MANIFEST.in
README.md
__init__.py
bottle.py
help.html
mookoo.py
setup.py
mookoo/LICENSE
mookoo/README.md
mookoo/__init__.py
mookoo/bottle.py
mookoo/help.html
mookoo/mookoo.py
mookoo/setup.py
mookoo.egg-info/PKG-INFO
mookoo.egg-info/SOURCES.txt
mookoo.egg-info/dependency_links.txt
mookoo.egg-info/entry_points.txt
mookoo.egg-info/top_level.txt