Metadata-Version: 1.1
Name: mookoo
Version: 0.1.0
Summary: Mock HTTP server
Home-page: https://github.com/gaorx/mookoo/
Author: GaoRongxin
Author-email: rongxin.gao@gmail.com
License: MIT
Platform: any
Classifier: Development Status :: 4 - Beta
Classifier: Environment :: Web Environment
Classifier: Intended Audience :: Developers
Classifier: License :: OSI Approved :: MIT License
Classifier: Operating System :: OS Independent
Classifier: Programming Language :: Python :: 2.7
Classifier: Topic :: Utilities
Classifier: Topic :: Software Development :: Libraries :: Python Modules
